mini_api/__init__.py
mini_api/api.py
mini_api-0.1.2.dist-info/METADATA
mini_api-0.1.2.dist-info/RECORD
mini_api-0.1.2.dist-info/WHEEL
mini_api-0.1.2.dist-info/top_level.txt
