Metadata-Version: 2.1
Name: mini-api
Version: 0.1.2
Summary: Minimalistic HTTP API with no frills
Home-page: https://github.com/mellon85/mini-api
Author: Dario Meloni
Author-email: mellon85@gmail.com
License: BSD 3-Clause
Platform: UNKNOWN
Classifier: Programming Language :: Python :: 3
Classifier: License :: OSI Approved :: BSD License
Classifier: Operating System :: OS Independent
